llvm2py/__init__.py
llvm2py/_llvm2py.cp310-win_amd64.pyd
llvm2py/ir/__init__.py
llvm2py/ir/block.py
llvm2py/ir/enum.py
llvm2py/ir/function.py
llvm2py/ir/global_object.py
llvm2py/ir/global_variable.py
llvm2py/ir/instruction.py
llvm2py/ir/module.py
llvm2py/ir/support.py
llvm2py/ir/type.py
llvm2py/ir/value.py
llvm2py-0.2.0b0.dist-info/METADATA
llvm2py-0.2.0b0.dist-info/WHEEL
llvm2py-0.2.0b0.dist-info/top_level.txt
llvm2py-0.2.0b0.dist-info/RECORD
