Metadata-Version: 2.2
Name: llvm2py
Version: 0.2.0b0
Summary: A library for analyzing LLVM IR in Python
Home-page: https://github.com/Papr1ka/llvm2py
Author: Papr1ka
Author-email: kirillpavlov4214@gmail.com
License: MIT
Keywords: llvm,analysis,ir,intermediate,presentation,representation,compiler,parser
Classifier: Development Status :: 4 - Beta
Classifier: Operating System :: Microsoft :: Windows
Classifier: Operating System :: POSIX
Classifier: Intended Audience :: Developers
Classifier: Intended Audience :: Education
Classifier: Intended Audience :: Science/Research
Classifier: Topic :: Scientific/Engineering
Classifier: Topic :: Software Development :: Libraries
Classifier: License :: OSI Approved :: MIT License
Classifier: Natural Language :: English
Classifier: Programming Language :: Python :: 3
Classifier: Programming Language :: Python :: 3.10
Classifier: Programming Language :: Python :: 3.11
Classifier: Programming Language :: Python :: 3.12
Classifier: Programming Language :: Python :: 3.13
Requires-Python: >=3.10
Dynamic: author
Dynamic: author-email
Dynamic: classifier
Dynamic: description
Dynamic: description-content-type
Dynamic: home-page
Dynamic: keywords
Dynamic: license
Dynamic: requires-python
Dynamic: summary
